tigergraph_mcp/__init__.py
tigergraph_mcp/main.py
tigergraph_mcp/server.py
tigergraph_mcp/tools/__init__.py
tigergraph_mcp/tools/db/__init__.py
tigergraph_mcp/tools/db/data_source/__init__.py
tigergraph_mcp/tools/db/data_source/create_data_source_tool.py
tigergraph_mcp/tools/db/data_source/drop_all_data_sources_tool.py
tigergraph_mcp/tools/db/data_source/drop_data_source_tool.py
tigergraph_mcp/tools/db/data_source/get_all_data_sources_tool.py
tigergraph_mcp/tools/db/data_source/get_data_source_tool.py
tigergraph_mcp/tools/db/data_source/preview_sample_data_tool.py
tigergraph_mcp/tools/db/data_source/update_data_source_tool.py
tigergraph_mcp/tools/db/gsql/__init__.py
tigergraph_mcp/tools/db/gsql/list_metadata_tool.py
tigergraph_mcp/tools/graph/__init__.py
tigergraph_mcp/tools/graph/data/__init__.py
tigergraph_mcp/tools/graph/data/load_data_tool.py
tigergraph_mcp/tools/graph/edge/__init__.py
tigergraph_mcp/tools/graph/edge/add_edge_tool.py
tigergraph_mcp/tools/graph/edge/add_edges_tool.py
tigergraph_mcp/tools/graph/edge/get_edge_data_tool.py
tigergraph_mcp/tools/graph/edge/has_edge_tool.py
tigergraph_mcp/tools/graph/node/__init__.py
tigergraph_mcp/tools/graph/node/add_node_tool.py
tigergraph_mcp/tools/graph/node/add_nodes_tool.py
tigergraph_mcp/tools/graph/node/clear_graph_data_tool.py
tigergraph_mcp/tools/graph/node/get_node_data_tool.py
tigergraph_mcp/tools/graph/node/get_node_edges_tool.py
tigergraph_mcp/tools/graph/node/has_node_tool.py
tigergraph_mcp/tools/graph/node/remove_node_tool.py
tigergraph_mcp/tools/graph/query/__init__.py
tigergraph_mcp/tools/graph/query/breadth_first_search_tool.py
tigergraph_mcp/tools/graph/query/create_query_tool.py
tigergraph_mcp/tools/graph/query/drop_query_tool.py
tigergraph_mcp/tools/graph/query/get_neighbors_tool.py
tigergraph_mcp/tools/graph/query/get_nodes_tool.py
tigergraph_mcp/tools/graph/query/install_query_tool.py
tigergraph_mcp/tools/graph/query/is_query_installed_tool.py
tigergraph_mcp/tools/graph/query/run_query_tool.py
tigergraph_mcp-0.2.4.dist-info/LICENSE
tigergraph_mcp-0.2.4.dist-info/METADATA
tigergraph_mcp-0.2.4.dist-info/WHEEL
tigergraph_mcp-0.2.4.dist-info/entry_points.txt
tigergraph_mcp-0.2.4.dist-info/RECORD
