Metadata-Version: 2.3
Name: tigergraph-mcp
Version: 0.2.4
Summary: 
Author: xunalei.lin
Author-email: xuanlei.lin@tigergraph.com
Requires-Python: >=3.10,<3.13
Classifier: Programming Language :: Python :: 3
Classifier: Programming Language :: Python :: 3.10
Classifier: Programming Language :: Python :: 3.11
Classifier: Programming Language :: Python :: 3.12
Requires-Dist: mcp (>=1.10.0,<2.0.0)
Requires-Dist: tigergraphx (>=0.2.15,<0.3.0)
